torchdrive/__init__.py
torchdrive/amp.py
torchdrive/attention.py
torchdrive/autograd.py
torchdrive/checkpoint.py
torchdrive/data.py
torchdrive/losses.py
torchdrive/matcher.py
torchdrive/positional_encoding.py
torchdrive/raymarcher.py
torchdrive/test_amp.py
torchdrive/test_attention.py
torchdrive/test_autograd.py
torchdrive/test_checkpoint.py
torchdrive/test_data.py
torchdrive/test_losses.py
torchdrive/test_matcher.py
torchdrive/test_positional_encoding.py
torchdrive/test_raymarcher.py
torchdrive/testing.py
torchdrive/models/__init__.py
torchdrive/models/bev.py
torchdrive/models/det.py
torchdrive/models/regnet.py
torchdrive/models/semantic.py
torchdrive/models/test_bev.py
torchdrive/models/test_det.py
torchdrive/models/test_regnet.py
torchdrive/models/test_semantic.py
torchdrive/transforms/__init__.py
torchdrive/transforms/bboxes.py
torchdrive/transforms/img.py
torchdrive/transforms/mat.py
torchdrive/transforms/test_bboxes.py
torchdrive/transforms/test_img.py
torchdrive/transforms/test_mat.py
torchdrive-0.0.1.dist-info/LICENSE
torchdrive-0.0.1.dist-info/METADATA
torchdrive-0.0.1.dist-info/WHEEL
torchdrive-0.0.1.dist-info/top_level.txt
torchdrive-0.0.1.dist-info/RECORD
