Metadata-Version: 2.1
Name: torchdrive
Version: 0.0.1
Summary: PyTorch library for BEV style perception models
Author: Tristan Rice
Author-email: rice@fn.lc
License: BSD-3-Clause
Keywords: pytorch,transformer,self-driving
Classifier: Programming Language :: Python :: 3
Requires-Python: >=3.7
License-File: LICENSE
Requires-Dist: pytorch3d
Requires-Dist: torchvision
Requires-Dist: scipy
